transfocate/__init__.py
transfocate/_version.py
transfocate/automated_checkout.py
transfocate/calculator.py
transfocate/checkout.py
transfocate/lens.py
transfocate/transfocator.py
transfocate/version.py
transfocate/table/MFX_EnergyLensInterlock_Tables_Transposed.xlsx
transfocate/table/__init__.py
transfocate/table/info.py
transfocate/table/ioc.py
transfocate/table/plc_table.py
transfocate/table/report.py
transfocate/tests/__init__.py
transfocate/tests/conftest.py
transfocate/tests/test_calculator.py
transfocate/tests/test_import.py
transfocate/tests/test_lens.py
transfocate/tests/test_transfocate.py
transfocate-0.5.9.dist-info/AUTHORS.rst
transfocate-0.5.9.dist-info/LICENSE.md
transfocate-0.5.9.dist-info/METADATA
transfocate-0.5.9.dist-info/WHEEL
transfocate-0.5.9.dist-info/top_level.txt
transfocate-0.5.9.dist-info/RECORD
