Metadata-Version: 2.1
Name: transfocate
Version: 0.5.9
Summary: Automated Calculation of Transfocator Focusing Optics
Author: SLAC National Accelerator Laboratory
License: Copyright (c) 2023, The Board of Trustees of the Leland Stanford Junior
Classifier: Development Status :: 2 - Pre-Alpha
Classifier: Natural Language :: English
Classifier: Programming Language :: Python :: 3
Requires-Python: >=3.9
License-File: LICENSE.md
License-File: AUTHORS.rst
Requires-Dist: databroker
Requires-Dist: bluesky
Requires-Dist: matplotlib
Requires-Dist: numpy
Requires-Dist: openpyxl
Requires-Dist: ophyd
Requires-Dist: pandas
Requires-Dist: pcdsdevices
Requires-Dist: prettytable
Requires-Dist: reportlab
Provides-Extra: doc
Requires-Dist: docs-versions-menu ; extra == 'doc'
Requires-Dist: sphinx ; extra == 'doc'
Requires-Dist: sphinxcontrib-jquery ; extra == 'doc'
Requires-Dist: sphinx-rtd-theme ; extra == 'doc'
Requires-Dist: ipython ; extra == 'doc'
Provides-Extra: test
Requires-Dist: pytest ; extra == 'test'
